apistar_settings.py
apistar_settings-0.2.0.dist-info/METADATA
apistar_settings-0.2.0.dist-info/RECORD
apistar_settings-0.2.0.dist-info/WHEEL
apistar_settings-0.2.0.dist-info/top_level.txt
