Metadata-Version: 2.1
Name: apistar-settings
Version: 0.2.0
Summary: A "Settings" component for API Star.
Home-page: UNKNOWN
License: UNKNOWN
Platform: UNKNOWN
Requires-Python: >=3.5
Requires-Dist: apistar (>=0.4)
